pelican/plugins/markdown_unrendered_metadata/__init__.py
pelican_markdown_unrendered_metadata/__init__.py
pelican_markdown_unrendered_metadata/markdown_metadata.py
pelican_markdown_unrendered_metadata/markdown_metadata_in_heading.py
pelican_markdown_unrendered_metadata/markdown_metadata_in_reference.py
pelican_markdown_unrendered_metadata-0.1.1.dist-info/LICENSE.txt
pelican_markdown_unrendered_metadata-0.1.1.dist-info/METADATA
pelican_markdown_unrendered_metadata-0.1.1.dist-info/WHEEL
pelican_markdown_unrendered_metadata-0.1.1.dist-info/top_level.txt
pelican_markdown_unrendered_metadata-0.1.1.dist-info/RECORD
