Metadata-Version: 2.1
Name: pelican-markdown-unrendered-metadata
Version: 0.1.1
Summary: Read Pelican metadata from link references
Home-page: https://github.com/BoniLindsley/pelican-markdown-unrendered-metadata
Author: Boni Lindsley
Author-email: boni@lindsley.xyz
License: UNKNOWN
Platform: UNKNOWN
Classifier: License :: OSI Approved :: MIT License
Classifier: Programming Language :: Python :: 3
Classifier: Programming Language :: Python :: 3.9
Requires-Python: >=3.9
License-File: LICENSE.txt
Requires-Dist: Markdown (>=3.3.4")
Requires-Dist: pelican (>=4.7.1")
Provides-Extra: dev
Requires-Dist: Markdown (>=3.3.4) ; extra == 'dev'
Requires-Dist: Sphinx (>=4.2.0) ; extra == 'dev'
Requires-Dist: black (>=21.9b0) ; extra == 'dev'
Requires-Dist: coverage[toml] (>=6.0.2) ; extra == 'dev'
Requires-Dist: mypy (>=0.910) ; extra == 'dev'
Requires-Dist: pytest (>=6.2.5) ; extra == 'dev'
Requires-Dist: recommonmark (>=0.7.1) ; extra == 'dev'
Requires-Dist: tox (>=3.24.4) ; extra == 'dev'
Requires-Dist: types-Markdown (>=3.3.6) ; extra == 'dev'
Requires-Dist: types-appdirs (>=1.4.1) ; extra == 'dev'
Requires-Dist: types-pkg-resources (>=0.1.3) ; extra == 'dev'
Requires-Dist: types-six (>=1.16.2) ; extra == 'dev'
